{"cameraMode":{"drawMode":0,"name":"Shaded","section":"Shading Mode"},"sceneLighting":true,"audioPlay":false,"sceneViewState":{"showFog":true,"showMaterialUpdate":false,"showSkybox":true,"showFlares":true,"showImageEffects":true,"showParticleSystems":true},"in2DMode":false,"pivot":{"x":-10.614715576171875,"y":1.7721842527389527,"z":-5.65578556060791},"rotation":{"x":-0.023899123072624208,"y":0.9603201746940613,"z":-0.0869627371430397,"w":-0.26391544938087466},"size":-0.521117091178894,"orthographic":false}